{"Mumbai": [[23355000, "in"]], "S\u00e3o Paulo": [[22046000, "br"]], "Nairobi": [[5545000, "ke"]], "Toronto": [[5429524, "ca"]], "Monterrey": [[4295000, "mx"]], "Amman": [[4007526, "jo"]], "Seattle": [[3789215, "us"]], "Tampa": [[2908063, "us"]], "Denver": [[2876625, "us"]], "Ecatepec": [[1656107, "mx"]], "Palembang": [[1452456, "id"]], "Tunis": [[1200000, "tn"]], "Chelyabinsk": [[1202371, "ru"]], "Lisbon": [[506654, "pt"], [8896, "us"], [5372, "us"]], "Tallinn": [[434562, "ee"]], "Klang": [[878000, "my"]], "Teresina": [[847430, "br"]], "Omaha": [[847819, "us"]], "Shizuoka": [[691185, "jp"]], "Kochi": [[677381, "in"]], "Palermo": [[674435, "it"], [5544, "us"]], "Durango": [[654876, "mx"], [20203, "us"]], "N\u0101nded": [[623708, "in"]], "Serang": [[613356, "id"]], "Jambi": [[602187, "id"]], "Uberl\u00e2ndia": [[604013, "br"]], "Tuxtla": [[598710, "mx"]], "General Santos": [[594446, "ph"]], "Mission Viejo": [[590249, "us"]], "Albany": [[586383, "us"], [19696, "us"], [89217, "us"], [62880, "us"], [34205, "au"]], "Knoxville": [[586048, "us"], [7199, "us"]], "Dresden": [[555805, "de"]], "Johor Bahru": [[497097, "my"]], "Ciudad L\u00f3pez Mateos": [[489937, "mx"]], "Brookhaven": [[484671, "us"], [55554, "us"], [10154, "us"], [8049, "us"], [5900, "us"]], "Greenville": [[484465, "us"], [130118, "us"], [29613, "us"], [26261, "us"], [12720, "us"], [9672, "us"], [9594, "us"], [8387, "us"], [7336, "us"], [6395, "us"], [5477, "us"]], "Americana": [[479472, "br"]], "Kaliningrad": [[475056, "ru"]], "San Juan": [[471389, "ar"], [331165, "pr"], [122180, "ph"], [72950, "do"], [37008, "us"]], "Marikina City": [[450741, "ph"]], "Sfax": [[453050, "tn"]], "Little Rock": [[439815, "us"]], "Mogi das Cruzes": [[424633, "br"]], "Tver": [[419363, "ru"]], "Kisumu": [[409928, "ke"]], "Szczecin": [[403833, "pl"]], "Lancaster": [[401524, "us"], [343304, "us"], [52234, "gb"], [44447, "us"], [42948, "us"], [39228, "us"], [25649, "us"], [8043, "us"]], "Miyazaki": [[398307, "jp"]], "Bh\u0101tp\u0101ra": [[386019, "in"]], "Thanh H\u00f3a": [[393294, "vn"]], "Tec\u00e1mac": [[364579, "mx"]], "Bydgoszcz": [[358614, "pl"]], "Itaquaquecetuba": [[352801, "br"]], "Haarlem": [[349957, "nl"]], "Victorville": [[346789, "us"]], "Yeosu": [[341994, "kr"], [273761, "kr"]], "Kawagoe": [[337931, "jp"]], "Tarsus": [[339676, "tr"]], "W\u014fnju": [[330854, "kr"]], "Markham": [[328966, "ca"], [12314, "us"]], "Bij\u0101pur": [[327427, "in"]], "Lansing": [[324286, "us"], [27402, "us"], [11949, "us"], [11329, "us"]], "Purnea": [[310817, "in"]], "Santa Clarita": [[312446, "us"]], "Chalco": [[310130, "mx"], [11456, "us"]], "Makurdi": [[292645, "ng"]], "Fukushima": [[286742, "jp"]], "Crato": [[273883, "br"], [273883, "br"]], "Limoges": [[283823, "fr"]], "Craiova": [[269506, "ro"]], "Cascavel": [[257172, "br"]], "Tallahassee": [[257601, "us"]], "Damaturu": [[255895, "ng"]], "Kuala Terengganu": [[255109, "my"]], "Arua": [[250000, "ug"]], "Verona": [[252520, "it"], [13413, "us"], [13233, "us"], [6221, "us"]], "North Las Vegas": [[251974, "us"]], "Caruaru": [[242094, "br"]], "San Bernardo": [[246762, "cl"]], "Yato": [[237445, "jp"]], "Juazeiro do Norte": [[225230, "br"]], "Visalia": [[237386, "us"]], "Kamianske": [[235066, "ua"]], "Machala": [[231260, "ec"]], "Kasukabe": [[229932, "jp"]], "Burnaby": [[232755, "ca"]], "Orsk": [[230414, "ru"]], "Burgas": [[226868, "bg"]], "Engels": [[225752, "ru"]], "Hickory": [[218323, "us"]], "Lubuklinggau": [[208225, "id"]], "Ziguinchor": [[205294, "sn"]], "Frisco": [[200490, "us"]], "Gibraltar": [[187083, "gi"]], "Waterbury": [[189614, "us"], [5141, "us"]], "Tachikawa": [[180880, "jp"]], "La Plata": [[186527, "ar"], [9631, "us"]], "Sioux Falls": [[187239, "us"]], "Cabo Frio": [[186227, "br"]], "Modena": [[184727, "it"]], "Calbayog City": [[183851, "ph"]], "Reggio di Calabria": [[182703, "it"]], "Burlington": [[183314, "ca"], [131043, "us"], [109763, "us"], [28474, "us"], [27059, "us"], [24691, "us"], [22587, "us"], [17069, "us"], [9607, "us"], [9224, "us"]], "Jaunpur": [[180362, "in"]], "Tunja": [[179263, "co"]], "Obuase": [[180460, "gh"]], "Langsa": [[178334, "id"]], "Ciudad Valles": [[176935, "mx"]], "Zabrze": [[174349, "pl"]], "Danbury": [[176030, "us"], [6500, "gb"]], "Oceanside": [[175742, "us"], [31185, "us"]], "Olsztyn": [[173599, "pl"]], "Bytom": [[171515, "pl"]], "Comodoro Rivadavia": [[173266, "ar"]], "Banyuwangi": [[172424, "id"]], "Marysville": [[170009, "us"], [24949, "us"], [12476, "us"], [9672, "us"]], "San Luis": [[169947, "ar"], [132470, "gt"], [32850, "us"]], "Ambato": [[165185, "ec"]], "Ten\u0101li": [[164937, "in"]], "Tangjin": [[163762, "kr"]], "Bragan\u00e7a Paulista": [[160665, "br"]], "Nazilli": [[156748, "tr"]], "B\u0101lurgh\u0101t": [[153279, "in"]], "Erode": [[151184, "in"]], "Gwangyang": [[151834, "kr"]], "Riobamba": [[146324, "ec"]], "Topeka": [[147458, "us"]], "Joliet": [[147344, "us"]], "Colima": [[137383, "mx"]], "Tiruvann\u0101malai": [[138243, "in"]], "Zama": [[130608, "jp"]], "Panama City": [[136133, "us"]], "Tabaco": [[133868, "ph"]], "Kent": [[132319, "us"], [29646, "us"], [13325, "us"], [6067, "ca"]], "Seto": [[127653, "jp"]], "Johnson City": [[127571, "us"], [14161, "us"]], "T\u00e2y Ninh": [[126370, "vn"]], "Leiria": [[126897, "pt"]], "Leeuwarden": [[125778, "nl"]], "Pforzheim": [[125542, "de"]], "Gingoog": [[124648, "ph"]], "Derbent": [[123720, "ru"]], "Bergamo": [[119806, "it"]], "Barretos": [[119243, "br"]], "Redding": [[121313, "us"], [9209, "us"]], "St. George": [[120899, "us"]], "Chico": [[117668, "us"]], "St. Cloud": [[115028, "us"], [54579, "us"]], "Kamagaya": [[109525, "jp"]], "Bukittinggi": [[113326, "id"]], "Brandon": [[113279, "us"], [9145, "gb"], [48859, "ca"], [24289, "us"], [9372, "us"]], "Novyy Urengoy": [[113254, "ru"]], "Kamyshin": [[111100, "ru"]], "Ciudad Mante": [[112061, "mx"]], "Trier": [[110636, "de"]], "Bedford": [[106940, "gb"], [49049, "us"], [22388, "us"], [17831, "us"], [14752, "us"], [14126, "us"], [12457, "us"], [7240, "us"], [5220, "us"]], "Manzini": [[110508, "sz"]], "Crawley": [[106597, "gb"]], "Wembley": [[102856, "gb"]], "Jalp\u0101iguri": [[107341, "in"]], "Thunder Bay": [[107909, "ca"]], "Pavlohrad": [[106082, "ua"]], "Yevpatoriya": [[106158, "ua"]], "Alchevsk": [[105398, "ua"]], "Bolzano": [[107317, "it"]], "Mansfield": [[106556, "gb"], [73326, "us"], [72419, "us"], [25977, "us"], [23761, "us"], [8538, "us"], [5604, "us"]], "Azare": [[105687, "ng"]], "Maumere": [[104285, "id"]], "Tourcoing": [[97368, "fr"]], "Biak": [[103610, "id"]], "Satu Mare": [[102411, "ro"]], "Legnica": [[101133, "pl"]], "Mumias": [[99987, "ke"]], "Gangtok": [[100286, "in"]], "Red Deer": [[100418, "ca"]], "Charlottesville": [[100416, "us"]], "Woodbridge": [[100187, "us"], [7749, "gb"], [8868, "us"]], "Shumen": [[97719, "bg"]], "Takasagoch\u014d-takasemachi": [[88223, "jp"]], "Tucuru\u00ed": [[76337, "br"]], "Saint-Ouen": [[51108, "fr"]], "Bilecik": [[81723, "tr"]], "Saint-Maur-des-Foss\u00e9s": [[74859, "fr"]], "Chal\u00e1ndri": [[74192, "gr"]], "Rub\u00ed": [[77464, "es"]], "Cachoeira do Sul": [[74694, "br"]], "Thornton Heath": [[65812, "gb"]], "Musashimurayama": [[71579, "jp"]], "Kiyosu": [[69680, "jp"]], "Frontera": [[70160, "mx"], [22795, "mx"], [10520, "ar"]], "Noisy-le-Grand": [[68183, "fr"]], "Inverness": [[70000, "gb"], [17235, "ca"], [7414, "us"], [7376, "us"]], "Sunyani": [[70299, "gh"]], "Courcouronnes": [[67967, "fr"]], "G\u00e4vle": [[68635, "se"]], "Villa Dom\u00ednico": [[62315, "ar"]], "Amozoc": [[60517, "mx"]], "Dewsbury": [[62945, "gb"]], "Kitale": [[63245, "ke"]], "Sinop": [[64544, "tr"], [8961, "br"]], "Ruislip": [[58217, "gb"]], "Stryy": [[59325, "ua"]], "Lorient": [[57149, "fr"]], "Serrinha": [[56829, "br"]], "Braintree": [[53477, "gb"], [37190, "us"]], "Carson City": [[58756, "us"]], "Magong": [[56435, "tw"]], "Jelgava": [[55972, "lv"]], "Vaslui": [[55407, "ro"]], "Senhor do Bonfim": [[48471, "br"]], "Mikkeli": [[54665, "fi"]], "Morden": [[48233, "gb"], [8668, "ca"]], "Irvington": [[54035, "us"], [6473, "us"]], "Whangarei": [[52600, "nz"]], "Oak Park": [[52381, "us"], [29431, "us"], [13730, "us"]], "Surbiton": [[45132, "gb"]], "Nelson": [[49300, "nz"], [29135, "gb"], [10664, "ca"]], "Hollister": [[48992, "us"]], "Emiliano Zapata": [[39702, "mx"], [12309, "mx"]], "Havant": [[45826, "gb"]], "Merthyr Tudful": [[43820, "gb"]], "Bellinzona": [[43220, "ch"]], "Jaguaquara": [[41498, "br"]], "North Lauderdale": [[44262, "us"]], "Le Kremlin-Bic\u00eatre": [[25334, "fr"]], "Whitney": [[43072, "us"]], "Blyth": [[37339, "gb"]], "Guarda": [[42541, "pt"]], "Si Sa Ket": [[42405, "th"]], "La Barca": [[35345, "mx"]], "Aberdare": [[39550, "gb"]], "Kisii": [[37531, "ke"]], "Panaji": [[40017, "in"]], "Mochudi": [[39700, "bw"]], "Annapolis": [[39223, "us"]], "Janu\u00e1ria": [[34811, "br"]], "Macuspana": [[30661, "mx"]], "Pierrefitte-sur-Seine": [[30306, "fr"]], "Ojuelos de Jalisco": [[32357, "mx"]], "East Meadow": [[37358, "us"]], "Aventura": [[36987, "us"]], "Bezons": [[29383, "fr"]], "Rayleigh": [[32150, "gb"]], "Schiltigheim": [[31894, "fr"]], "Belleville": [[36069, "us"], [50716, "ca"], [40897, "us"]], "Farnworth": [[30271, "gb"]], "Chuhuiv": [[33144, "ua"]], "Taibao": [[35000, "tw"]], "Foster City": [[33901, "us"]], "Plympton": [[29899, "gb"]], "Goussainville": [[30637, "fr"]], "Viana": [[26689, "br"]], "P\u00e9fki": [[21415, "gr"]], "B\u0159evnov": [[26275, "cz"]], "Tr\u00edpoli": [[30866, "gr"]], "Concei\u00e7\u00e3o do Araguaia": [[27115, "br"]], "Billericay": [[27998, "gb"]], "Leyton": [[14184, "gb"]], "Kanchanaburi": [[29581, "th"]], "Ba\u010dka Palanka": [[29449, "rs"]], "Estoril": [[26399, "pt"]], "Tapiales": [[23586, "ar"]], "Highgate": [[10955, "gb"]], "Le Grand-Quevilly": [[25698, "fr"]], "Ki\u010devo": [[27067, "mk"]], "Magdalena de Kino": [[23359, "mx"]], "Thornaby on Tees": [[24741, "gb"]], "Orly": [[23801, "fr"]], "Atlatlahucan": [[22079, "mx"]], "Svay Rieng": [[23956, "kh"]], "Litherland": [[22242, "gb"]], "Itupiranga": [[21301, "br"]], "San Juan Zitlaltepec": [[19600, "mx"]], "Longjumeau": [[21221, "fr"]], "San Lorenzo": [[25388, "us"], [7629, "pr"], [47626, "ar"], [3000, "bo"]], "Paracuru": [[21196, "br"]], "Mohale\u2019s Hoek": [[24992, "ls"]], "Vukovar": [[24938, "hr"]], "Copiague": [[23716, "us"]], "West Puente Valley": [[23629, "us"]], "Carteret": [[23408, "us"]], "Yonabaru": [[19494, "jp"]], "Bellshill": [[20650, "gb"]], "Le M\u00e9e-sur-Seine": [[20816, "fr"]], "Hadleigh": [[18300, "gb"], [8253, "gb"]], "Sunny Isles Beach": [[21804, "us"]], "Virovitica": [[21291, "hr"]], "Mountlake Terrace": [[21338, "us"]], "Porthcawl": [[16005, "gb"]], "Santiago Tuxtla": [[15681, "mx"]], "Tilbury": [[12450, "gb"]], "Tlaxcala": [[14692, "mx"]], "Lynbrook": [[19448, "us"]], "Baildon": [[15360, "gb"]], "Mineola": [[19207, "us"], [5919, "us"]], "\u0110\u00f4ng H\u00e0": [[17662, "vn"]], "Pedreiras": [[13638, "br"]], "Brookfield": [[18310, "us"], [39115, "us"], [17013, "us"]], "Bebington": [[15768, "gb"]], "Burke Centre": [[18236, "us"]], "Plung\u0117": [[18042, "lt"]], "Esquimalt": [[17655, "ca"]], "Ojus": [[17462, "us"]], "Sudbury": [[14950, "gb"], [88054, "ca"], [18940, "us"], [13063, "gb"]], "Zaghouan": [[16911, "tn"]], "Yauco": [[16802, "pr"]], "Allestree": [[13622, "gb"]], "West University Place": [[15585, "us"]], "Sonoita": [[12849, "mx"]], "Radvili\u0161kis": [[15275, "lt"]], "Quthing": [[15000, "ls"]], "Pierre": [[14659, "us"]], "Carnoustie": [[11394, "gb"]], "Bacalar": [[11084, "mx"]], "Tixkokob": [[10968, "mx"]], "La Grange Park": [[13178, "us"]], "Cornelius": [[12822, "us"], [30257, "us"]], "Roby": [[7254, "gb"]], "Larbert": [[9143, "gb"]], "Patchogue": [[12321, "us"]], "Chuy": [[9675, "uy"]], "Amatl\u00e1n de los Reyes": [[9123, "mx"]], "Tocantin\u00f3polis": [[8750, "br"]], "Home Gardens": [[11442, "us"]], "Leven": [[8850, "gb"]], "Guadalupe Yancuictlalpan": [[6385, "mx"]], "North Lindenhurst": [[10584, "us"]], "Altdorf": [[9401, "ch"]], "Wistaston": [[8117, "gb"]], "Frampton Cotterell": [[6520, "gb"]], "Brechin": [[7199, "gb"]], "Bladensburg": [[9408, "us"]], "Long Ashton": [[6044, "gb"]], "Hoylake": [[5710, "gb"]], "Magor": [[6140, "gb"]], "Mount Rainier": [[8093, "us"]], "Conshohocken": [[8047, "us"]], "Aizkraukle": [[7745, "lv"]], "Ru\u0161e": [[7351, "si"]], "South Monrovia Island": [[7192, "us"]], "Nyack": [[7156, "us"]], "Ewa Villages": [[7118, "us"]], "Twin Rivers": [[7067, "us"]], "South Valley Stream": [[6930, "us"]], "Balvi": [[6334, "lv"]], "Arroyo": [[6134, "pr"]], "Jamesburg": [[5885, "us"]], "Mount Carmel": [[5724, "us"], [7016, "us"], [5372, "us"], [5294, "us"]], "Rochelle Park": [[5613, "us"]], "Friendship Heights Village": [[5225, "us"]], "P\u0101vilosta": [[1035, "lv"]], "Waitangi": [[300, "nz"]], "Kobarid": [[4, "si"]], "Rio Rancho": [[99178, "us"]], "Solikamsk": [[94628, "ru"]], "Menderes": [[93796, "tr"]], "Higashi-Matsuyama": [[92302, "jp"]], "Velikiye Luki": [[91435, "ru"]], "Terre Haute": [[92490, "us"]], "Flensburg": [[90164, "de"]], "Paredes": [[86854, "pt"]], "Brindisi": [[87141, "it"]], "Cheektowaga": [[86813, "us"]], "Pariaman": [[85485, "id"]], "Ushiku": [[84637, "jp"]], "Napa": [[85239, "us"]], "Jelenia G\u00f3ra": [[84306, "pl"]], "Moriyama": [[82526, "jp"]], "Tual": [[82955, "id"]], "Port Huron": [[82970, "us"]], "Luj\u00e1n": [[81749, "ar"]], "Springdale": [[81125, "us"], [13547, "us"], [11166, "us"]], "Maizuru": [[79886, "jp"]], "Valdosta": [[79820, "us"]], "Pharr": [[79112, "us"]], "Layton": [[78014, "us"]], "Texarkana": [[77964, "us"], [29657, "us"]], "Honj\u014d": [[77045, "jp"]], "S\u00f6ke": [[77341, "tr"]], "Mafra": [[76685, "pt"]], "Missouri City": [[75457, "us"]], "Mangalagiri": [[73613, "in"]], "Kawartha Lakes": [[75423, "ca"]], "Riberalta": [[74014, "bo"]], "Chapayevsk": [[72778, "ru"]], "Itapira": [[72967, "br"]], "Redmond": [[71929, "us"], [34240, "us"]], "Verkhnyaya Pyshma": [[71241, "ru"]], "Badvel": [[70626, "in"]], "Novomoskovs\u2019k": [[70749, "ua"]], "Sipalay": [[70070, "ph"]], "Rocklin": [[68823, "us"]], "Sabanalarga": [[68535, "co"]], "Rogers": [[68669, "us"], [13490, "us"]], "Otukpo": [[68220, "ng"]], "Feodosiya": [[67993, "ua"]], "Casper": [[67598, "us"]], "Most": [[66034, "cz"]], "Kalush": [[66406, "ua"]], "Ban Lam Sam Kaeo": [[63271, "th"]], "Kristiansand": [[64057, "no"]], "Grevenbroich": [[63620, "de"]], "Velika Gorica": [[63517, "hr"]], "Roeselare": [[62301, "be"]], "Mayag\u00fcez": [[62579, "pr"]], "Waltham": [[62495, "us"], [6413, "gb"]], "San Luis Obispo": [[62290, "us"]], "Naro-Fominsk": [[62002, "ru"]], "Tr\u00edkala": [[61653, "gr"]], "Gadsden": [[60944, "us"]], "Greenwood": [[59458, "us"], [42429, "us"], [19961, "us"], [9063, "us"], [5833, "us"]], "Kosai": [[58423, "jp"]], "Kanduk\u016br": [[57246, "in"]], "Bobbili": [[56819, "in"]], "Irpin\u2019": [[56806, "ua"]], "Hidaka": [[55241, "jp"]], "Lozova": [[55827, "ua"]], "Canterbury": [[55240, "gb"], [5074, "us"]], "Amal\u0101puram": [[53231, "in"]], "Normal": [[54469, "us"]], "Progreso": [[53958, "mx"], [12557, "mx"], [5944, "us"]], "Jagti\u0101l": [[53213, "in"]], "Tuni": [[53425, "in"]], "Apopka": [[53447, "us"]], "Little Elm": [[53126, "us"]], "Ibbenb\u00fcren": [[51904, "de"]], "Jaguari\u00fana": [[51907, "br"]], "Ravensburg": [[50623, "de"]], "Erftstadt": [[49801, "de"]], "Borovichi": [[50144, "ru"]], "Itarar\u00e9": [[50105, "br"]], "Poway": [[49323, "us"]], "Jasdan": [[48483, "in"]], "St. Louis Park": [[48662, "us"]], "Kutno": [[47557, "pl"]], "Ban Plai Bua Phatthana": [[46274, "th"]], "Glenview": [[47308, "us"]], "Poso": [[47110, "id"]], "New Philadelphia": [[46698, "us"]], "Roskilde": [[44285, "dk"]], "Aksay": [[46018, "ru"]], "El Dorado Hills": [[45599, "us"]], "Lake Ridge": [[44430, "us"]], "Urbandale": [[44379, "us"]], "Dikili": [[44172, "tr"]], "Kobayashi": [[44034, "jp"]], "Voluntari": [[42944, "ro"]], "Southington": [[43763, "us"]], "E\u1e6d \u1e6caiyiba": [[43100, "il"]], "Istres": [[43133, "fr"]], "Gifhorn": [[42519, "de"]], "Orl\u00e2ndia": [[42678, "br"]], "Spassk-Dal\u2019niy": [[41127, "ru"]], "Timmins": [[41788, "ca"]], "Wentzville": [[41784, "us"]], "Freiberg": [[40885, "de"]], "Lokeren": [[41057, "be"]], "Nowa S\u00f3l": [[39721, "pl"]], "Coppell": [[41421, "us"]], "Tonbridge": [[40356, "gb"]], "Wei\u00dfenfels": [[40409, "de"]], "Anglet": [[38929, "fr"]], "Holyoke": [[40117, "us"]], "Ettlingen": [[39339, "de"]], "Sakuragawa": [[39692, "jp"]], "Marinha Grande": [[38681, "pt"]], "Guariba": [[38499, "br"]], "Krasnyy Sulin": [[38284, "ru"]], "Houghton le Spring": [[36746, "gb"]], "Mullaittivu": [[37339, "lk"]], "Bathurst": [[36801, "au"], [18154, "ca"]], "Papenburg": [[37579, "de"]], "Holly Springs": [[37812, "us"], [15442, "us"], [6239, "us"]], "Cottage Grove": [[37604, "us"], [11892, "us"], [7143, "us"]], "San Blas": [[37478, "mx"]], "Lierre": [[36646, "be"]], "Koryazhma": [[36607, "ru"]], "Netishyn": [[36921, "ua"]], "Yorktown": [[36618, "us"], [11111, "us"]], "Agudos": [[36524, "br"]], "Warrnambool": [[35214, "au"]], "Udhampur": [[35507, "in"]], "Tucker": [[36395, "us"]], "La Ciotat": [[35174, "fr"]], "Cutral-C\u00f3": [[35465, "ar"]], "Lage": [[35047, "de"]], "Upper Arlington": [[35366, "us"]], "Shr\u012brangapattana": [[34135, "in"]], "Randolph": [[34362, "us"], [25651, "us"]], "French Valley": [[33818, "us"]], "Korschenbroich": [[33066, "de"]], "Lebowakgomo": [[33308, "za"]], "Ciudad Tec\u00fan Um\u00e1n": [[33426, "gt"]], "Liptovsk\u00fd Mikul\u00e1\u0161": [[32593, "sk"]], "J\u00fclich": [[32632, "de"]], "Zentsujich\u00f3": [[32073, "jp"]], "Naumburg": [[32402, "de"], [5028, "de"]], "S\u00e3o Miguel Arcanjo": [[32769, "br"]], "Chancay": [[32312, "pe"]], "Dobryanka": [[32676, "ru"]], "Ridgecrest": [[32684, "us"]], "East Kelowna": [[32655, "ca"]], "Mioveni": [[31998, "ro"]], "La Calera": [[32227, "ar"]], "Primorsko-Akhtarsk": [[32180, "ru"]], "Zapala": [[32097, "ar"]], "Pekin": [[32045, "us"]], "Kyzyl-Kyya": [[31727, "kg"]], "Weil am Rhein": [[30175, "de"]], "Morro Agudo": [[31620, "br"]], "Pontes e Lacerda": [[29381, "br"]], "Uran": [[30439, "in"]], "Banning": [[31221, "us"]], "Tewksbury": [[31002, "us"], [5830, "us"]], "Synel\u2019nykove": [[30724, "ua"]], "Yoshinaga": [[28899, "jp"]], "Cihuatl\u00e1n": [[30241, "mx"]], "Los Altos": [[30089, "us"]], "Schwedt (Oder)": [[29920, "de"]], "Villa Regina": [[30028, "ar"]], "Rietberg": [[29466, "de"]], "Fortuna Foothills": [[29485, "us"]], "Aleysk": [[28528, "ru"]], "La Concordia": [[29003, "ec"]], "Springe": [[28951, "de"]], "North Attleborough": [[29116, "us"]], "Mei\u00dfen": [[28044, "de"]], "Balakliia": [[28868, "ua"]], "Novyy Rozdil": [[28745, "ua"]], "Kakuda": [[28623, "jp"]], "Gorlice": [[27597, "pl"]], "Silvassa": [[27359, "in"]], "Wetter (Ruhr)": [[27441, "de"]], "Takahagi": [[27863, "jp"]], "Salinas Victoria": [[27848, "mx"]], "Tualatin": [[27837, "us"]], "East Chicago": [[27817, "us"]], "J\u00e1szber\u00e9ny": [[27439, "hu"]], "Santa Rita do Passa Quatro": [[27502, "br"]], "Gloversville": [[27512, "us"]], "Summerlin South": [[27506, "us"]], "Overath": [[27040, "de"]], "Bergerac": [[26833, "fr"]], "Oakleaf Plantation": [[27252, "us"]], "Gubkinskiy": [[27238, "ru"]], "Bushey": [[25763, "gb"]], "Waynesboro": [[26694, "us"], [22630, "us"], [5422, "us"]], "Hermanus": [[25153, "za"]], "West Milford": [[26409, "us"]], "Pfaffenhofen": [[25917, "de"]], "Tinipuka": [[26021, "id"]], "Mason City": [[26005, "us"]], "Neiba": [[25731, "do"]], "Otradnoye": [[25623, "ru"]], "Maaseik": [[25201, "be"]], "Kose": [[24965, "jp"]], "Muret": [[24945, "fr"]], "Salzkotten": [[25062, "de"]], "Champlin": [[25268, "us"]], "Rosemount": [[25207, "us"]], "Droitwich": [[23504, "gb"]], "Warstein": [[24842, "de"]], "Hodon\u00edn": [[24512, "cz"]], "Leoben": [[24645, "at"]], "Brasil\u00e9ia": [[24765, "br"]], "Auburn Hills": [[24748, "us"]], "Swatara": [[24685, "us"]], "Khajur\u0101ho": [[24481, "in"]], "Waldkraiburg": [[23442, "de"]], "Springfield Township": [[24232, "us"], [19639, "us"], [5586, "us"], [5048, "us"]], "Amstetten": [[23656, "at"]], "Konstancin-Jeziorna": [[23694, "pl"]], "Sokolov": [[23033, "cz"]], "Kalach-na-Donu": [[23947, "ru"]], "Alice Springs": [[23726, "au"]], "Palatka": [[23738, "us"], [21452, "ru"]], "Waycross": [[23671, "us"]], "Partiz\u00e1nske": [[22653, "sk"]], "Belton": [[23642, "us"], [22885, "us"], [5865, "us"]], "Bronnitsy": [[22567, "ru"]], "Montrose": [[23478, "us"], [11955, "gb"], [7810, "us"], [5208, "us"]], "Loves Park": [[23371, "us"]], "Kilk\u00eds": [[22914, "gr"]], "Whyalla": [[21742, "au"]], "Velsk": [[22776, "ru"]], "Gj\u00f8vik": [[22719, "no"]], "Kaltenkirchen": [[21813, "de"]], "East Peoria": [[22546, "us"]], "Colorado": [[22345, "br"]], "Golden Valley": [[21886, "us"], [8673, "us"]], "Stadtallendorf": [[21456, "de"]], "Le Ray": [[21665, "us"]], "Lewistown": [[21614, "us"], [5987, "us"]], "Lutz": [[21456, "us"]], "Salmon Creek": [[21299, "us"]], "Duarte": [[21271, "us"]], "Rumoi": [[20841, "jp"]], "Bayou Cane": [[20829, "us"]], "Nov\u00e9 Mesto nad V\u00e1hom": [[20066, "sk"]], "Korntal-M\u00fcnchingen": [[19679, "de"]], "Logansport": [[20608, "us"]], "Nikolsk": [[20572, "ru"], [7996, "ru"]], "Swansboro": [[20507, "us"]], "Gro\u00dfburgwedel": [[20369, "de"]], "Ozark": [[20482, "us"], [11562, "us"]], "M\u011bln\u00edk": [[19559, "cz"]], "H\u00f6rstel": [[20141, "de"]], "Beroun": [[19641, "cz"]], "Lake Shore": [[20260, "us"], [7909, "us"]], "Skegness": [[19579, "gb"]], "Shenandoah": [[20192, "us"], [17840, "us"]], "Miamisburg": [[20143, "us"]], "Brambleton": [[20081, "us"]], "Junqueir\u00f3polis": [[20066, "br"]], "Ban Tha Kham": [[19939, "th"]], "Yeppoon": [[19003, "au"]], "\u00c4\u00e4nekoski": [[19919, "fi"]], "Mead Valley": [[19925, "us"]], "Iiyama": [[19800, "jp"]], "Barrhead": [[19813, "gb"]], "Corner Brook": [[19806, "ca"]], "Jakobstad": [[19436, "fi"]], "Casa de Oro-Mount Helix": [[19635, "us"]], "Ro\u017e\u0148ava": [[19190, "sk"]], "Rio Rico": [[19601, "us"]], "Szigethalom": [[17596, "hu"]], "Rivi\u00e8re-du-Loup": [[19447, "ca"]], "Bad Pyrmont": [[19090, "de"]], "Doln\u00fd Kub\u00edn": [[18905, "sk"]], "Bad Driburg": [[19002, "de"]], "Sartell": [[18926, "us"]], "Contamana": [[18921, "pe"]], "Lake Butler": [[18917, "us"]], "Aberystwyth": [[18093, "gb"]], "Otrokovice": [[17879, "cz"]], "Rufino": [[18727, "ar"]], "Surovikino": [[18685, "ru"]], "Port Isabel": [[18686, "us"]], "San Blas Atempa": [[18406, "mx"]], "Rancho Mirage": [[18528, "us"]], "Belooz\u00ebrskiy": [[18297, "ru"]], "Monor": [[18084, "hu"]], "Wallingford Center": [[18322, "us"]], "Cimarron Hills": [[18285, "us"]], "Isfana": [[18244, "kg"]], "Ginsheim-Gustavsburg": [[16807, "de"]], "Mi\u0119dzyrzec Podlaski": [[17117, "pl"]], "Rockland": [[17909, "us"], [8616, "us"]], "Scarsdale": [[17871, "us"]], "Lous\u00e3": [[17604, "pt"]], "Milan\u00f3wek": [[16419, "pl"]], "Hinsdale": [[17637, "us"]], "Plast": [[17508, "ru"]], "Pom\u00e1z": [[17139, "hu"]], "Plymouth Township": [[17421, "us"]], "Bethpage": [[17215, "us"]], "Freiberg am Neckar": [[15968, "de"]], "Pi\u00f1as": [[16981, "ec"]], "Cham": [[16907, "de"]], "Palos Hills": [[17060, "us"]], "Sylacauga": [[16982, "us"]], "Fort Hunt": [[16858, "us"]], "Ro\u017enov pod Radho\u0161t\u011bm": [[16398, "cz"]], "Neston": [[15221, "gb"]], "Saint-Basile-le-Grand": [[16736, "ca"]], "Ishinari": [[16328, "jp"]], "\u014carai": [[15992, "jp"]], "Olecko": [[16508, "pl"]], "Edmundston": [[16580, "ca"]], "Gar\u00f0ab\u00e6r": [[16299, "is"]], "Lymington": [[15726, "gb"]], "Portachuelo": [[16408, "bo"]], "Herisau": [[15780, "ch"]], "Gun Barrel City": [[16292, "us"]], "Mebane": [[16262, "us"]], "Daigo": [[16142, "jp"]], "Say\u014d": [[15958, "jp"]], "Seven Pagodas": [[15172, "in"]], "Greater Napanee": [[15892, "ca"]], "Nymburk": [[15154, "cz"]], "Kalininsk": [[15821, "ru"]], "Easthampton": [[15829, "us"]], "Putyvl\u2019": [[15778, "ua"]], "Kysuck\u00e9 Nov\u00e9 Mesto": [[15132, "sk"]], "West Norriton": [[15703, "us"]], "Kuusamo": [[15688, "fi"]], "Riverdale": [[15594, "us"], [13077, "us"], [8838, "us"]], "Rahden": [[15441, "de"]], "Narragansett": [[15550, "us"]], "Barwon Heads": [[14165, "au"]], "Hohenstein-Ernstthal": [[14607, "de"]], "Obanazawa": [[15332, "jp"]], "Nazar\u00e9": [[15158, "pt"]], "Damascus": [[15094, "us"], [12024, "us"]], "Betsukai": [[15018, "jp"]], "Ibikon": [[13610, "ch"]], "Whitman": [[14961, "us"]], "Radomir": [[14880, "bg"]], "Kondrovo": [[14857, "ru"]], "Salem Lakes": [[14852, "us"]], "Campbellsville": [[14772, "us"]], "Bad Wurzach": [[14651, "de"]], "Stein bei N\u00fcrnberg": [[13996, "de"]], "Royse City": [[14702, "us"]], "Hartsville": [[14693, "us"], [11284, "us"]], "Sanderstead": [[12777, "gb"]], "Southern Pines": [[14657, "us"]], "Chelsfield": [[14507, "gb"]], "Eberbach": [[14460, "de"]], "Priverno": [[14365, "it"]], "Santa Branca": [[14534, "br"]], "Jennings": [[14575, "us"], [9315, "us"]], "Tlayacapan": [[14467, "mx"]], "Metuchen": [[14543, "us"]], "Alaus\u00ed": [[14294, "ec"]], "Gernsbach": [[14296, "de"]], "Hampton Bays": [[14280, "us"]], "Mill Valley": [[14259, "us"]], "Gardendale": [[14177, "us"]], "Gr\u00fcnstadt": [[13422, "de"]], "Ystrad Mynach": [[13500, "gb"]], "Steamboat Springs": [[14087, "us"]], "Dubovka": [[13988, "ru"]], "A\u00dflar": [[13656, "de"]], "Zhovkva": [[13834, "ua"]], "Allouez": [[13894, "us"]], "Selston": [[12596, "gb"]], "Kupino": [[13777, "ru"]], "Mont-Laurier": [[13779, "ca"]], "Hilpoltstein": [[13624, "de"]], "Thomaston": [[13759, "us"], [7623, "us"]], "Otley": [[13668, "gb"]], "Rottingdean": [[13651, "gb"]], "Radnevo": [[13554, "bg"]], "Lake Forest Park": [[13504, "us"]], "Wehr": [[13098, "de"]], "Lindale": [[13442, "us"]], "Berkeley Heights": [[13417, "us"]], "Colac": [[12547, "au"]], "Powell": [[13375, "us"], [6253, "us"]], "Wasserburg am Inn": [[12691, "de"]], "Tonosh\u014d": [[13078, "jp"]], "Hajd\u00fas\u00e1mson": [[12961, "hu"]], "Suamico": [[13052, "us"]], "Sooke": [[13001, "ca"]], "Pfarrkirchen": [[12677, "de"]], "Berwick-Upon-Tweed": [[12043, "gb"]], "Gyomaendr\u0151d": [[12784, "hu"]], "Santiago Amoltepec": [[12683, "mx"]], "Broussard": [[12700, "us"]], "Bad Urach": [[12472, "de"]], "Vakhrusheve": [[12197, "ua"]], "Elfers": [[12637, "us"]], "Irmo": [[12483, "us"]], "Trophy Club": [[12451, "us"]], "S\u00e3o Sebasti\u00e3o da Grama": [[12355, "br"]], "Elkhorn": [[12404, "us"]], "Cottonwood": [[12253, "us"]], "Cecil": [[12245, "us"]], "Lincolnwood": [[12245, "us"]], "Nov\u00fd Bor": [[11616, "cz"]], "Ladenburg": [[11537, "de"]], "Tabapu\u00e3": [[12103, "br"]], "Wang Saphung": [[11992, "th"]], "Saj\u00f3szentp\u00e9ter": [[11679, "hu"]], "Chuquicamata": [[11941, "cl"]], "Pilis": [[11678, "hu"]], "Hole\u0161ov": [[11579, "cz"]], "Maxh\u00fctte-Haidhof": [[11575, "de"]], "Dolinsk": [[11765, "ru"]], "Padiham": [[10098, "gb"]], "Tucson Estates": [[11758, "us"]], "Mezdra": [[11719, "bg"]], "Aesch": [[10352, "ch"]], "Mena": [[11670, "ua"], [5261, "us"]], "Dingman": [[11674, "us"]], "Putnam Valley": [[11654, "us"]], "Mistelbach": [[11559, "at"]], "Svidn\u00edk": [[11096, "sk"]], "Cedarburg": [[11603, "us"]], "Saman\u00e1": [[11432, "do"]], "Silver City": [[11561, "us"]], "Montmagny": [[11491, "ca"]], "Elwood": [[11439, "us"], [9180, "us"]], "Jiman\u00ed": [[11414, "do"]], "Ki\u00e1to": [[9812, "gr"]], "Bellmawr": [[11359, "us"]], "Doctor Phillips": [[11347, "us"]], "Gro\u00df-Enzersdorf": [[11206, "at"]], "Etropole": [[11292, "bg"]], "Lamesa": [[11241, "us"]], "Knezha": [[11124, "bg"]], "Broomall": [[11154, "us"]], "Ogano": [[11078, "jp"]], "Warka": [[11035, "pl"]], "Hammelburg": [[11037, "de"]], "Ayd\u0131nc\u0131k": [[11088, "tr"]], "Lowes Island": [[11111, "us"]], "Nazyvayevsk": [[11101, "ru"]], "Lake Grove": [[11056, "us"]], "Pedro de Toledo": [[10967, "br"]], "General Salgado": [[10961, "br"]], "Lollar": [[10395, "de"]], "Aberbargoed": [[9184, "gb"]], "Saks": [[10763, "us"]], "Kami-furano": [[10709, "jp"]], "Bischofshofen": [[10540, "at"]], "Southwater": [[10025, "gb"]], "Bentley": [[8782, "au"]], "Or\u015fova": [[10441, "ro"]], "Mildenhall": [[10315, "gb"]], "Barcs": [[10501, "hu"]], "Kauniainen": [[9486, "fi"]], "Pitkyaranta": [[10479, "ru"]], "Sumner": [[10427, "us"]], "Vidor": [[10403, "us"]], "Yaotsu": [[10321, "jp"]], "Cajobi": [[10341, "br"]], "Saint-F\u00e9licien": [[10278, "ca"]], "Moimenta da Beira": [[10212, "pt"]], "Bonham": [[10250, "us"]], "Bad Orb": [[10020, "de"]], "Erquelinnes": [[9940, "be"]], "Opochka": [[10148, "ru"]], "Old Saybrook": [[10118, "us"]], "Kurort Steinbach-Hallenberg": [[9681, "de"]], "Wood River": [[10051, "us"]], "Milford Township": [[10046, "us"]], "Key Largo": [[9954, "us"]], "Winterville": [[9931, "us"]], "Jilotl\u00e1n de los Dolores": [[9917, "mx"]], "Towcester": [[9252, "gb"]], "Sarapu\u00ed": [[9836, "br"]], "N\u0103s\u0103ud": [[9587, "ro"]], "Itasca": [[9805, "us"]], "Leeton": [[8623, "au"]], "Yamakita": [[9702, "jp"]], "Heiligenhafen": [[9211, "de"]], "Boaz": [[9704, "us"]], "Visselh\u00f6vede": [[9629, "de"]], "Ilsenburg": [[9526, "de"]], "Ledbury": [[9290, "gb"]], "Manduri": [[9592, "br"]], "Palmeira d\u2019Oeste": [[9596, "br"]], "St. Pete Beach": [[9587, "us"]], "F\u00fcrstenau": [[9439, "de"]], "Silsbee": [[9540, "us"]], "Eidson Road": [[9531, "us"]], "L\u00fcchow": [[9420, "de"]], "Sa\u00dfnitz": [[9320, "de"]], "Miltenberg": [[9355, "de"]], "Cameron": [[9501, "us"], [5304, "us"]], "Independent Hill": [[9499, "us"]], "Huedin": [[9346, "ro"]], "Lambertville": [[9394, "us"]], "Madras": [[9340, "us"]], "New Richmond": [[9302, "us"]], "Reserve": [[9280, "us"]], "Torgelow": [[9153, "de"]], "Marathon": [[9271, "us"]], "Freetown": [[9251, "us"]], "Sredets": [[9237, "bg"]], "Wendover": [[7399, "gb"]], "Madeira": [[9245, "us"]], "Furth im Wald": [[9093, "de"]], "Brewood": [[7329, "gb"]], "Matamata": [[7910, "nz"]], "Griesbach": [[9055, "de"]], "Scotchtown": [[9174, "us"]], "Calimesa": [[9160, "us"]], "Ystradgynlais": [[8092, "gb"]], "\u014ctaki": [[9049, "jp"]], "Woodmoor": [[9117, "us"]], "Poli\u010dka": [[8813, "cz"]], "Vinhais": [[9066, "pt"]], "Karkkila": [[8969, "fi"]], "Ve\u013ek\u00fd Meder": [[8828, "sk"]], "Fort Knox": [[8965, "us"]], "Sodankyl\u00e4": [[8942, "fi"]], "Eceabat": [[8912, "tr"]], "Boonton": [[8919, "us"]], "Bang Mun Nak": [[8756, "th"]], "Rhinelander": [[8830, "us"]], "Absecon": [[8818, "us"]], "Monson": [[8811, "us"]], "Berching": [[8702, "de"]], "Rathdrum": [[8764, "us"]], "Pont-Rouge": [[8723, "ca"]], "Succasunna": [[8681, "us"]], "Newstead": [[8674, "us"]], "Dobrada": [[8592, "br"]], "London Grove": [[8615, "us"]], "Mourni\u00e9s": [[7553, "gr"]], "Laitila": [[8520, "fi"]], "Narrabri": [[7606, "au"]], "White Horse": [[8512, "us"]], "Derecske": [[8403, "hu"]], "Yadrin": [[8387, "ru"]], "Seaton": [[8413, "gb"]], "Grafenau": [[8256, "de"]], "Ostseebad K\u00fchlungsborn": [[7896, "de"]], "Peebles": [[8376, "gb"]], "Warsash": [[7183, "gb"]], "Jessup": [[8359, "us"]], "Knittlingen": [[8048, "de"]], "Buckhannon": [[8351, "us"]], "Kalamp\u00e1ka": [[8330, "gr"]], "Mahtomedi": [[8294, "us"]], "West Earl": [[8272, "us"]], "Lanark": [[8253, "gb"]], "Druid Hills": [[8244, "us"]], "Westlake Village": [[8217, "us"]], "High Ackworth": [[7049, "gb"]], "Hurbanovo": [[8041, "sk"]], "Black Mountain": [[8162, "us"]], "Kirchheimbolanden": [[7802, "de"]], "Croton-on-Hudson": [[8095, "us"]], "Lake Dallas": [[8063, "us"]], "Ramstein-Miesenbach": [[7876, "de"]], "Berchtesgaden": [[7780, "de"]], "Polg\u00e1r": [[7889, "hu"]], "Aztec": [[7963, "us"]], "Baltimore Highlands": [[7959, "us"]], "Herzogenburg": [[7771, "at"]], "Lincolnshire": [[7893, "us"]], "Itobi": [[7831, "br"]], "Fremantle": [[7459, "au"]], "Los Fresnos": [[7837, "us"]], "DeFuniak Springs": [[7823, "us"]], "Seville": [[7812, "us"]], "Waterboro": [[7803, "us"]], "Gerolstein": [[7676, "de"]], "Mattighofen": [[6524, "at"]], "Rhinebeck": [[7768, "us"]], "Tenterden": [[7735, "gb"]], "Cheraw": [[7757, "us"]], "Quarryville": [[7741, "us"]], "Grove": [[7726, "us"], [7178, "gb"]], "Belinskiy": [[7694, "ru"]], "Oundle": [[5735, "gb"]], "Pressbaum": [[7559, "at"]], "Oceano": [[7678, "us"]], "Wivenhoe": [[7637, "gb"]], "Allegany": [[7663, "us"]], "Catigu\u00e1": [[7603, "br"]], "Lake of the Woods": [[7649, "us"]], "Mattersburg": [[7349, "at"]], "Renchen": [[7361, "de"]], "Pikeville": [[7531, "us"]], "Porto Cristo": [[7355, "es"]], "Fairlawn": [[7514, "us"]], "Tateishi": [[7389, "jp"]], "Chibougamau": [[7504, "ca"]], "Nov\u00e1 Ba\u0148a": [[7364, "sk"]], "Nisa": [[7450, "pt"]], "Keystone Heights": [[7449, "us"]], "Topanga": [[7449, "us"]], "Haapaj\u00e4rvi": [[7438, "fi"]], "Gundelsheim": [[7254, "de"]], "Orosi": [[7441, "us"]], "South Berwick": [[7420, "us"]], "Baywood": [[7389, "us"]], "Humberston": [[5634, "gb"]], "Fresia": [[7328, "cl"]], "Cannington": [[5929, "au"]], "N\u00fd\u0159any": [[6996, "cz"]], "St. Johnsbury": [[7299, "us"]], "New Cumberland": [[7288, "us"]], "Yass": [[6506, "au"]], "North Berwick": [[6605, "gb"]], "Crystal City": [[7255, "us"]], "Tranqueras": [[7235, "uy"]], "Kurri Kurri": [[6044, "au"]], "Skaneateles": [[7198, "us"]], "Downside": [[6564, "gb"]], "Esher": [[6743, "gb"]], "Granville": [[5500, "au"], [6503, "us"], [5916, "us"]], "Oberndorf bei Salzburg": [[5815, "at"]], "Buzia\u015f": [[7023, "ro"]], "Whitemarsh Island": [[7058, "us"]], "Lipany": [[6484, "sk"]], "Nambucca Heads": [[6327, "au"]], "Edwardsburgh/Cardinal": [[6959, "ca"]], "Prairie View": [[6944, "us"]], "Tommot": [[6935, "ru"]], "Newton Grange": [[5341, "gb"]], "M\u00fcncheberg": [[6870, "de"]], "Chestertown": [[6878, "us"]], "Tabernacle": [[6868, "us"]], "Newbiggin-by-the-Sea": [[6308, "gb"]], "Loomis": [[6866, "us"]], "Maulbronn": [[6588, "de"]], "Peace River": [[6842, "ca"]], "Santo Ant\u00f4nio do Pinhal": [[6767, "br"]], "Kostenets": [[6777, "bg"]], "East Buffalo": [[6806, "us"]], "Mount Hope": [[6781, "us"]], "Annaburg": [[6731, "de"]], "Ibr\u00e1ny": [[6648, "hu"]], "Schladming": [[6660, "at"]], "Straldzha": [[6635, "bg"]], "Blairsville": [[6654, "us"]], "Slave Lake": [[6651, "ca"]], "Catasauqua": [[6599, "us"]], "Strensall": [[6047, "gb"]], "Varshets": [[6500, "bg"]], "Orlovista": [[6574, "us"]], "Wentworth Falls": [[6076, "au"]], "Rossford": [[6562, "us"]], "Bad Marienberg": [[5961, "de"]], "Camp Swift": [[6553, "us"]], "Swanton": [[6530, "us"]], "Friedland": [[6472, "de"]], "West Tamworth": [[5342, "au"]], "S\u00e3o Martinho": [[6226, "pt"]], "Drayton": [[5489, "gb"]], "Boischatel": [[6465, "ca"]], "Martf\u016f": [[6169, "hu"]], "Headley": [[5613, "gb"]], "Arandu": [[6351, "br"]], "Lincroft": [[6348, "us"]], "Carmel Hamlet": [[6345, "us"]], "Barnhart": [[6318, "us"]], "Delle": [[5690, "fr"]], "Ohio": [[6308, "us"]], "Zubtsov": [[6300, "ru"]], "Kenedy": [[6223, "us"]], "Hethersett": [[5691, "gb"]], "Figueir\u00f3 dos Vinhos": [[6169, "pt"]], "Limbourg": [[5939, "be"]], "Pol\u00fdgyros": [[6121, "gr"]], "Lanett": [[6151, "us"]], "Bartonville": [[6113, "us"]], "Shihoro": [[6078, "jp"]], "Harlan": [[6089, "us"]], "Senatobia": [[6086, "us"]], "Monchique": [[6045, "pt"]], "Writtle": [[5383, "gb"]], "Brezoi": [[6022, "ro"]], "Sealy": [[5957, "us"]], "Vidigueira": [[5932, "pt"]], "Westville": [[5943, "us"]], "Trooper": [[5936, "us"]], "Zebulon": [[5917, "us"]], "Pocahontas": [[5887, "us"]], "Clyde": [[5886, "us"]], "Stratmoor": [[5883, "us"]], "Arroyo de la Luz": [[5811, "es"]], "Hellertown": [[5831, "us"]], "Schwarzheide": [[5652, "de"]], "Kremast\u00ed": [[5363, "gr"]], "Sewickley": [[5808, "us"]], "Schrozberg": [[5741, "de"]], "Palmview": [[5774, "us"]], "Elbridge": [[5761, "us"]], "Strawberry": [[5759, "us"]], "Santa Ernestina": [[5681, "br"]], "Starke": [[5647, "us"]], "Gadebusch": [[5530, "de"]], "Waihi": [[5310, "nz"]], "Hotton": [[5531, "be"]], "South Huntingdon": [[5589, "us"]], "Chackbay": [[5573, "us"]], "Otterberg": [[5389, "de"]], "Falcon Heights": [[5528, "us"]], "Hlubok\u00e1 nad Vltavou": [[5419, "cz"]], "Indian Wells": [[5470, "us"]], "S\u0103li\u015fte": [[5421, "ro"]], "Bear Valley Springs": [[5442, "us"]], "Grieskirchen": [[5002, "at"]], "Honeoye Falls": [[5428, "us"]], "Violet": [[5424, "us"]], "Littlefield": [[5423, "us"]], "New Hempstead": [[5410, "us"]], "Wonthaggi": [[4965, "au"]], "Marilla": [[5373, "us"]], "Momignies": [[5309, "be"]], "St. Paul Park": [[5362, "us"]], "East Moriches": [[5359, "us"]], "Mattawa": [[5349, "us"]], "Bederkesa": [[5227, "de"]], "Oshamambe": [[5329, "jp"]], "Belle Fourche": [[5341, "us"]], "Fairport": [[5305, "us"]], "Berri": [[4103, "au"]], "Ronneburg": [[5026, "de"]], "West Yarmouth": [[5271, "us"]], "N\u00e9a Anchi\u00e1los": [[5132, "gr"]], "Holdrege": [[5255, "us"]], "Deer Lake": [[5249, "ca"]], "Chiny": [[5175, "be"]], "Vereya": [[5123, "ru"]], "Lake Wildwood": [[5208, "us"]], "Firthcliffe": [[5178, "us"]], "Weisenberg": [[5140, "us"]], "Bierut\u00f3w": [[5065, "pl"]], "Rainsville": [[5123, "us"]], "Colebrookdale": [[5075, "us"]], "Chukhloma": [[5015, "ru"]], "Mullins": [[5010, "us"]], "Svolv\u00e6r": [[4686, "no"]], "General Conesa": [[2958, "ar"]], "Hlatikulu": [[2748, "sz"]], "Coroico": [[2319, "bo"]], "Kaikoura": [[2210, "nz"]], "Wagin": [[1824, "au"]], "Ouyen": [[1191, "au"]], "Meningie": [[1118, "au"]], "Wilcannia": [[745, "au"]], "Adelaide River": [[353, "au"]], "Pine Creek": [[328, "au"]], "Euxton": [[9993, "gb"]], "Reyes": [[7376, "bo"]], "Khandyga": [[6796, "ru"]], "Swanscombe": [[6300, "gb"]], "Lydiate": [[6308, "gb"]], "Tamchen": [[6307, "mx"]], "Chernyshevskiy": [[5137, "ru"]], "Ste. Anne": [[5003, "ca"]], "Nata": [[4794, "bw"]], "El Mait\u00e9n": [[4269, "ar"]], "De-Kastri": [[3615, "ru"]], "Egvekinot": [[2248, "ru"]], "Corocoro": [[1884, "bo"]], "Put\u2019 Lenina": [[298, "ru"]], "Kangersuatsiaq": [[200, "gl"]], "Soldado Bartra": [[10, "pe"]], "Omchak": [[10, "ru"]], "Shalaurova": [[10, "ru"]], "Agapa": [[10, "ru"]], "Olen\u00ebk": [[10, "ru"]]}